buildhub/__init__.py
buildhub/test_buildhub.py
python_buildhub-0.0.1.dist-info/LICENSE
python_buildhub-0.0.1.dist-info/METADATA
python_buildhub-0.0.1.dist-info/WHEEL
python_buildhub-0.0.1.dist-info/top_level.txt
python_buildhub-0.0.1.dist-info/RECORD
