Metadata-Version: 2.1
Name: python-buildhub
Version: 0.0.1
Summary: Python interface to Buildhub service
Home-page: https://github.com/peterbe/python-buildhub
Author: Peter Bengtsson
Author-email: mail@peterbe.com
License: MPL2
Platform: UNKNOWN
Classifier: License :: OSI Approved :: Mozilla Public License 2.0 (MPL 2.0)
Classifier: Programming Language :: Python :: 3
Classifier: Programming Language :: Python :: 3.5
Classifier: Programming Language :: Python :: 3.6
Classifier: Programming Language :: Python :: 3.7
Requires-Dist: requests
Provides-Extra: dev
Requires-Dist: twine ; extra == 'dev'
Requires-Dist: therapist ; extra == 'dev'
Requires-Dist: black ; extra == 'dev'
Requires-Dist: flake8 ; extra == 'dev'
Requires-Dist: bumpversion ; extra == 'dev'
Requires-Dist: tox ; extra == 'dev'
